mlscaffold/__init__.py
mlscaffold/cli.py
mlscaffold/templates.py
mlscaffold-0.2.1.dist-info/licenses/LICENSE
mlscaffold-0.2.1.dist-info/METADATA
mlscaffold-0.2.1.dist-info/WHEEL
mlscaffold-0.2.1.dist-info/entry_points.txt
mlscaffold-0.2.1.dist-info/top_level.txt
mlscaffold-0.2.1.dist-info/RECORD
