Metadata-Version: 2.4
Name: mlscaffold
Version: 0.2.1
Summary: Create a ready-to-use ML project structure with one command.
Author-email: Chanuka Dilshan <mchanuka72@gmail.com>
License: MIT License
Project-URL: Homepage, https://github.com/Chanukaa2002/mlscaffold
Project-URL: Repository, https://github.com/Chanukaa2002/mlscaffold
Requires-Python: >=3.8
License-File: LICENSE
Requires-Dist: questionary>=2.0.0
Dynamic: license-file
